epsg_constants/__init__.py
epsg_constants/epsg_number.py
epsg_constants-10.11.0.dist-info/AUTHORS.rst
epsg_constants-10.11.0.dist-info/LICENSE
epsg_constants-10.11.0.dist-info/METADATA
epsg_constants-10.11.0.dist-info/WHEEL
epsg_constants-10.11.0.dist-info/top_level.txt
epsg_constants-10.11.0.dist-info/RECORD
