Metadata-Version: 2.1
Name: epsg-constants
Version: 10.11.0
Summary: Python constants with EPSG numbers for coordinate reference systems, based on EPSG dataset v10.011
Home-page: https://github.com/TomasJohansson/epsg_constants_4python
Author: Tomas Johansson
Author-email: pypi@programmerare.com
License: MIT license
Keywords: EPSG constants,CRS,Coordinate Reference Systems
Platform: UNKNOWN
Classifier: Development Status :: 5 - Production/Stable
Classifier: Intended Audience :: Developers
Classifier: License :: OSI Approved :: MIT License
Classifier: Natural Language :: English
Classifier: Topic :: Scientific/Engineering :: GIS
Classifier: Programming Language :: Python :: 2.7
Classifier: Programming Language :: Python :: 3
Classifier: Programming Language :: Python :: 3.0
Classifier: Programming Language :: Python :: 3.1
Classifier: Programming Language :: Python :: 3.2
Classifier: Programming Language :: Python :: 3.3
Classifier: Programming Language :: Python :: 3.4
Classifier: Programming Language :: Python :: 3.5
Classifier: Programming Language :: Python :: 3.6
Classifier: Programming Language :: Python :: 3.7
Classifier: Programming Language :: Python :: 3.8
Classifier: Programming Language :: Python :: 3.9
Requires-Python: >=2.7
